{
  "version": "1",
  "metadata": {
    "marimo_version": "0.23.1",
    "script_metadata_hash": null
  },
  "cells": [
    {
      "id": "Hbol",
      "code_hash": "1d0db38904205bec4d6f6f6a1f6cec3e",
      "outputs": [
        {
          "type": "data",
          "data": {
            "text/plain": ""
          }
        }
      ],
      "console": []
    },
    {
      "id": "MJUe",
      "code_hash": "7307bd041069df882892ad81261217c5",
      "outputs": [
        {
          "type": "data",
          "data": {
            "text/markdown": "<span class=\"markdown prose dark:prose-invert contents\"><h1 id=\"batch-analytics-analyse-des-donnees-batch\">Batch Analytics - Analyse des Donnees Batch</h1>\n<span class=\"paragraph\">Ce notebook permet d'analyser les donnees chargees par le DAG Airflow :</span>\n<ol>\n<li><strong>Inventaire</strong> - Sante des stocks par entrepot</li>\n<li><strong>Livraisons</strong> - Statut des livraisons fournisseurs</li>\n<li><strong>Support</strong> - KPIs des tickets par canal</li>\n</ol>\n<h2 id=\"traitement-batch-quotidien\">Traitement Batch Quotidien</h2>\n<span class=\"paragraph\">Le DAG <code>ecommerce_batch_pipeline</code> execute chaque jour a minuit et :</span>\n<ol>\n<li>Depose les fichiers sources dans MinIO (bucket <code>raw</code>)</li>\n<li>Charge les donnees dans les tables <code>staging.*</code></li>\n<li>Genere les tables analytiques dans <code>analytics.*</code></li>\n</ol>\n<h2 id=\"tables-disponibles\">Tables Disponibles</h2>\n<ul>\n<li><code>staging.inventory_snapshot</code> - Snapshot quotidien des stocks</li>\n<li><code>staging.supplier_deliveries</code> - Livraisons fournisseurs</li>\n<li><code>staging.support_tickets</code> - Tickets support</li>\n<li><code>analytics.daily_inventory_health</code> - Sante des stocks</li>\n<li><code>analytics.daily_support_kpis</code> - KPIs support</li>\n</ul></span>"
          }
        }
      ],
      "console": []
    },
    {
      "id": "vblA",
      "code_hash": "50d68ad84c9fd1e8dd4817d4f396f966",
      "outputs": [
        {
          "type": "data",
          "data": {
            "text/plain": ""
          }
        }
      ],
      "console": [
        {
          "type": "stream",
          "name": "stdout",
          "text": "PostgreSQL: postgres:5432/warehouse\n",
          "mimetype": "text/plain"
        }
      ]
    },
    {
      "id": "bkHC",
      "code_hash": null,
      "outputs": [],
      "console": []
    }
  ]
}